{"USA": "en_US", "Canada": ["en_CA", "fr_CA"], "Mexico": "es_MX", "Puerto Rico": ["es_PR", "en_PR"], "United Arab Emirates": ["en_AE", "ar_AE"], "Israel": "he_IL", "Belgium": ["nl_BE", "fr_BE"], "Czechia": "cs_CZ", "Denmark": "da_DK", "Germany": "de_DE", "Greece": "el_GR", "Spain": "es_ES", "Estonia": "en_EE", "France": "fr_FR", "Croatia": "hr_HR", "Hungary": "hu_HU", "Ireland": "en_IE", "Iceland": "is_IS", "Italy": "it_IT", "Luxembourg": ["de_LU", "fr_LU"], "Netherlands": "nl_NL", "Norway": "no_NO", "Austria": "de_AT", "Poland": "pl_PL", "Portual": "pt_PT", "Romania": "ro_RO", "Slovakia": "en_SK", "Switzerland": ["de_CH", "fr_CH", "it_CH"], "Slovenia": "sl_SI", "Finland": "fi_FI", "Sweden": "sv_SE", "Great Britain": "en_GB", "Lithuania": "en_LT", "Latvia": "en_LV", "China": "zh_CN", "Hong Kong": ["en_HK", "zh_HK"], "Macau": ["en_MO", "zh_MO"], "Taiwan": "zh_TW", "South Korea": "ko_KR", "Japan": "ja_JP", "Australia": "en_AU", "New Zealand": "en_NZ", "Singapore": "en_SG", "Thailand": ["en_TH", "th_TH"]}