{ "timestamp": "06102024-1314", "parkhouses": [ { "name": "Liebig-Center", "free_spaces": 244, "occupied_spaces": 6, "max_spaces": 250 }, { "name": "neust\u00c3\u20acdter", "free_spaces": 475, "occupied_spaces": 333, "max_spaces": 808 }, { "name": "Rathaus", "free_spaces": 182, "occupied_spaces": 68, "max_spaces": 250 }, { "name": "Selters Tor", "free_spaces": 98, "occupied_spaces": 60, "max_spaces": 158 }, { "name": "Am Bahnhof", "free_spaces": 172, "occupied_spaces": 67, "max_spaces": 239 } ] }
