{ "timestamp": "16092024-1248", "parkhouses": [ { "name": "Dern-Passage", "free_spaces": 120, "occupied_spaces": 79, "max_spaces": 199 }, { "name": "Karstadt", "free_spaces": 112, "occupied_spaces": 268, "max_spaces": 380 }, { "name": "Liebig-Center", "free_spaces": 243, "occupied_spaces": 7, "max_spaces": 250 }, { "name": "neust\u00c3\u20acdter", "free_spaces": 205, "occupied_spaces": 603, "max_spaces": 808 }, { "name": "Rathaus", "free_spaces": 66, "occupied_spaces": 104, "max_spaces": 170 }, { "name": "Selters Tor", "free_spaces": 32, "occupied_spaces": 126, "max_spaces": 158 }, { "name": "Westanlage", "free_spaces": 217, "occupied_spaces": 18, "max_spaces": 235 }, { "name": "Am Bahnhof", "free_spaces": 152, "occupied_spaces": 87, "max_spaces": 239 } ] }
