{ "timestamp": "20112024-1620", "parkhouses": [ { "name": "Dern-Passage", "free_spaces": 120, "occupied_spaces": 79, "max_spaces": 199 }, { "name": "Karstadt", "free_spaces": 126, "occupied_spaces": 254, "max_spaces": 380 }, { "name": "Liebig-Center", "free_spaces": 237, "occupied_spaces": 13, "max_spaces": 250 }, { "name": "neust\u00c3\u20acdter", "free_spaces": 425, "occupied_spaces": 463, "max_spaces": 888 }, { "name": "Rathaus", "free_spaces": 49, "occupied_spaces": 121, "max_spaces": 170 }, { "name": "Selters Tor", "free_spaces": 72, "occupied_spaces": 86, "max_spaces": 158 }, { "name": "Westanlage", "free_spaces": 310, "occupied_spaces": 0, "max_spaces": 310 }, { "name": "Am Bahnhof", "free_spaces": 147, "occupied_spaces": 92, "max_spaces": 239 } ] }
