{ "timestamp": "27112024-2033", "parkhouses": [ { "name": "Liebig-Center", "free_spaces": 241, "occupied_spaces": 9, "max_spaces": 250 }, { "name": "neust\u00c3\u20acdter", "free_spaces": 613, "occupied_spaces": 275, "max_spaces": 888 }, { "name": "Rathaus", "free_spaces": 82, "occupied_spaces": 168, "max_spaces": 250 }, { "name": "Selters Tor", "free_spaces": 116, "occupied_spaces": 42, "max_spaces": 158 }, { "name": "Westanlage", "free_spaces": 310, "occupied_spaces": 0, "max_spaces": 310 }, { "name": "Am Bahnhof", "free_spaces": 192, "occupied_spaces": 47, "max_spaces": 239 } ] }
