{ "timestamp": "28112024-1645", "parkhouses": [ { "name": "Dern-Passage", "free_spaces": 120, "occupied_spaces": 79, "max_spaces": 199 }, { "name": "Karstadt", "free_spaces": 96, "occupied_spaces": 284, "max_spaces": 380 }, { "name": "Liebig-Center", "free_spaces": 233, "occupied_spaces": 17, "max_spaces": 250 }, { "name": "neust\u00c3\u20acdter", "free_spaces": 305, "occupied_spaces": 583, "max_spaces": 888 }, { "name": "Rathaus", "free_spaces": 8, "occupied_spaces": 162, "max_spaces": 170 }, { "name": "Selters Tor", "free_spaces": 47, "occupied_spaces": 111, "max_spaces": 158 }, { "name": "Westanlage", "free_spaces": 310, "occupied_spaces": 0, "max_spaces": 310 }, { "name": "Am Bahnhof", "free_spaces": 167, "occupied_spaces": 72, "max_spaces": 239 } ] }
