{"text": " Da l\u00e4uft ihr Zeit, J\u00f6rg. Ich gr\u00fc\u00dfe euch. Liebe Freunde und Freunde, der Wert einer Gesellschaft, der Wert einer Gesellschaft, vermisst sich darin, wie sie mit den Schw\u00e4chsten umgeht. Wie steht die Politik, den kranken Menschen zur Seite, wenn wir Corona haben? Wie geht sie mit den Menschen, um deren Leben bedrohen ist? Wie helfen wir den Schw\u00e4chsten bei der Energiekrise und wie halten wir die Demokratie zusammen? Liebe Freunde und Freunde, die \u00f6kologische Transformation wird nur gelingen, wenn wir f\u00fcr soziale Sicherheit sorgen. Liebe Freunde, mein Name ist Markus Bockler, ich bin der sozialpolitische Sprecher der Gr\u00fcnen Landtagsfraktion. Ich habe die letzten Koalitionsvertr\u00e4ge mitverhandelt und wir k\u00f6nnen es wirklich wahrlich sehen lassen, wie wir diese Krisen gemeistert haben. Liebe Freunde und Freunde, lasst mich nur kurze Beispiele daf\u00fcr nennen. Wir haben ein bundesweit einmaliges Sozialbudget, das Matthias Wagner hatte schon erw\u00e4hnt, von 35 auf 130 Millionen erh\u00f6ht haben. Das sind nicht nur einfache Zahlen, liebe Freundinnen und Freunde. Wir haben Frauen geholfen, die vor Gewalt fl\u00fcchten. Wir haben Frauenhauspl\u00e4tze geschaffen. Wir haben Jugendliche geholfen, die keine Ausbildungspl\u00e4tze mehr finden, weil die Firmen vor der Insolvenz standen. Wir haben Langzeitarbeitslosen geholfen, die keine Perspektive mehr hatten, den wir Arbeitsmarktprogramme aufgelegt haben. Wir haben nat\u00fcrlich auch denjenigen geholfen, die in Not waren, durch Beratungsstrukturen, die wir damit halten. Liebe Freundinnen und Freunde, wir haben in den Koalitionsvertr\u00e4gen versprochen, dass wir f\u00fcr die soziale Sicherheit und das f\u00fcr soziale Gerechtigkeit sorgen. Liebe Freundinnen und Freunde, ihr k\u00f6nnt bei den Wahlk\u00e4mpfen an den St\u00e4nden sagen, wir haben Wort gehalten. Gr\u00fcne Hessen stehen f\u00fcr soziale Gerechtigkeit, liebe Freundinnen und Freunde. Aber machen wir uns nichts vor. Die wirklichen Krise, die noch l\u00e4uft, der Krieg in der Ukraine, die Abrechnung kommen erst noch im M\u00e4rz. Und die Menschen werden davon geschockt sein und sie werden Probleme haben bei der Energie-Grise. Sie werden von Energie-St\u00e4rf-Sperren bedroht sein. Sie werden von K\u00fcndigungen bedroht sein. Was wir jetzt brauchen, ist ein weiteres Entlastungspaket f\u00fcr Hessen, in dem wir daf\u00fcr sorgen, dass alles nicht eintritt. Wir m\u00fcssen den Menschen in Not helfen, weil nur das auch unsere Gesellschaft hier in Hessen zusammenh\u00e4lt. Liebe Freundinnen und Freunde. Deshalb setzen wir uns ein. F\u00fcr das ist keine K\u00fcndigung, dass wir die Beratungsstrukturen st\u00e4rken, dass wir f\u00fcr die Verein- und Einrichtungen, die wir alle brauchen werden, damit wir den Menschen geholfen werden. Wie beispielsweise den Tafeln. Es kann einfach nicht sein, dass Menschen, die Hunger erleiden, dass sie zu Tafeln gehen m\u00fcssen. Das finde ich schon schlimm genug, aber dass diese Tafeln ihre Arbeit nicht mehr nachgehen k\u00f6nnen. Das ist ein Skandal und deswegen haben wir ihnen geholfen. Es kann nicht sein, dass er ein so einem reichen Land wie Deutschland oder Hessen Menschen hungern m\u00fcssen. Das muss ein Ende haben, liebe Freundinnen und Freunde. Wir haben gro\u00dfe Probleme, die vor uns liegen werden. Ich werde als Sozialpolitischer Sprecher daf\u00fcr einsetzen, dass wir auf die schw\u00e4chsten Achten werden. Es kann tats\u00e4chlich werden, wenn wir nicht in den Koalitionsvertr\u00e4gen alles durchsetzen k\u00f6nnen, was gr\u00fcne Programm ist. Aber ich verspreche, dass ich f\u00fcr eine Gesellschaft einsetzen kann, die Anstand vorliebt, die Solidarit\u00e4t vorliebt und die Solidarit\u00e4t mit den Schw\u00e4chten vorliebt. Gemeinsam in der Landesregierung werden wir gr\u00fcne daf\u00fcr sorgen, dass wir niemanden zur\u00fccklassen. Das ist unsere Fliechenaufgabe und daf\u00fcr stehe ich mit meinem Mandat, liebe Freundinnen und Freunde. Und ein letzter Punkt, der mir sehr am Herzen liegt. Wir haben eine unfassbar gro\u00dfe sozialpolitische Herausforderung, das ist die Wohnungsnot. Und die war das in vor 2022. Es sind immer wieder neue, mehr soziale Wohnungen aus der Bindung gefallen, als wir geschaffen haben. Und wir haben zum ersten Mal Ende 2022 Tarek Al-Wazir, den Trend umzukehrt. Wir haben zum ersten Mal mehr Sozialbohnungen in Hessen geschaffen, als aus der Bindung gefallen sind. Liebe Freundinnen und Freunde, mit Gr\u00fcnen geht auch Wohnungspolitik. Und das m\u00fcssen wir fortsetzen. Liebe Freundinnen und Freunde. Wir machen uns nichts vor. Es wird so sein, dass diese Errungenschaften, die wir im Sozialbudget in vielen anderen Paketen geschafft haben, dass die FDP, die nach dem Motto arbeitet, wenn jeder f\u00fcr sich selbst dog ist, doch allen geholfen, dass die nur darauf warten, in ihren Antr\u00e4gen, all diese Errungenschaften, diese Erfolger r\u00fcckg\u00e4ngig zu machen. Das m\u00fcssen wir verhindern. Wir m\u00fcssen weiter die Anw\u00e4lte der Schw\u00e4chten sein. Eine Gesellschaft, bei welchem Wert, bemisst sich daran, wie es ihm mit den Schw\u00e4chten umgeht. Ich setze mich daf\u00fcr ein, dass ihn nach wie vor ihre Hauptaufmerksamkeit darauf legt. Darauf k\u00f6nnt ihr euch das f\u00fcr die Gespr\u00e4chsprechen. Danke.", "segments": [{"id": 0, "seek": 0, "start": 0.0, "end": 7.0, "text": " Da l\u00e4uft ihr Zeit, J\u00f6rg. Ich gr\u00fc\u00dfe euch. Liebe Freunde und Freunde, der Wert einer Gesellschaft,", "tokens": [3933, 31807, 5553, 9394, 11, 508, 2311, 70, 13, 3141, 677, 774, 11451, 10403, 13, 28790, 40016, 674, 40016, 11, 1163, 37205, 6850, 30006, 11], "temperature": 0.0, "avg_logprob": -0.27241065910270623, "compression_ratio": 1.623076923076923, "no_speech_prob": 0.15286003053188324}, {"id": 1, "seek": 0, "start": 7.0, "end": 13.0, "text": " der Wert einer Gesellschaft, vermisst sich darin, wie sie mit den Schw\u00e4chsten umgeht.", "tokens": [1163, 37205, 6850, 30006, 11, 26319, 45802, 3041, 4072, 259, 11, 3355, 2804, 2194, 1441, 17576, 10168, 6266, 1105, 46227, 13], "temperature": 0.0, "avg_logprob": -0.27241065910270623, "compression_ratio": 1.623076923076923, "no_speech_prob": 0.15286003053188324}, {"id": 2, "seek": 0, "start": 13.0, "end": 18.0, "text": " Wie steht die Politik, den kranken Menschen zur Seite, wenn wir Corona haben?", "tokens": [9233, 16361, 978, 29847, 11, 1441, 15913, 18493, 8397, 7147, 19748, 11, 4797, 1987, 18075, 3084, 30], "temperature": 0.0, "avg_logprob": -0.27241065910270623, "compression_ratio": 1.623076923076923, "no_speech_prob": 0.15286003053188324}, {"id": 3, "seek": 0, "start": 18.0, "end": 21.0, "text": " Wie geht sie mit den Menschen, um deren Leben bedrohen ist?", "tokens": [9233, 7095, 2804, 2194, 1441, 8397, 11, 1105, 48300, 15399, 2901, 340, 2932, 1418, 30], "temperature": 0.0, "avg_logprob": -0.27241065910270623, "compression_ratio": 1.623076923076923, "no_speech_prob": 0.15286003053188324}, {"id": 4, "seek": 0, "start": 21.0, "end": 27.0, "text": " Wie helfen wir den Schw\u00e4chsten bei der Energiekrise und wie halten wir die Demokratie zusammen?", "tokens": [9233, 29966, 1987, 1441, 17576, 10168, 6266, 4643, 1163, 35309, 74, 18619, 674, 3355, 27184, 1987, 978, 27802, 414, 14311, 30], "temperature": 0.0, "avg_logprob": -0.27241065910270623, "compression_ratio": 1.623076923076923, "no_speech_prob": 0.15286003053188324}, {"id": 5, "seek": 2700, "start": 27.0, "end": 34.0, "text": " Liebe Freunde und Freunde, die \u00f6kologische Transformation wird nur gelingen, wenn wir f\u00fcr soziale Sicherheit sorgen.", "tokens": [28790, 40016, 674, 40016, 11, 978, 4044, 74, 1132, 7864, 6531, 8663, 4578, 4343, 4087, 12343, 11, 4797, 1987, 2959, 31541, 68, 38778, 47972, 13], "temperature": 0.0, "avg_logprob": -0.14485943108274227, "compression_ratio": 1.6151079136690647, "no_speech_prob": 0.000552739598788321}, {"id": 6, "seek": 2700, "start": 34.0, "end": 39.0, "text": " Liebe Freunde, mein Name ist Markus Bockler, ich bin der sozialpolitische Sprecher der Gr\u00fcnen Landtagsfraktion.", "tokens": [28790, 40016, 11, 10777, 13866, 1418, 45041, 47672, 1918, 11, 1893, 5171, 1163, 31541, 27461, 7864, 1738, 265, 6759, 1163, 38908, 2866, 6607, 83, 12109, 69, 39694, 13], "temperature": 0.0, "avg_logprob": -0.14485943108274227, "compression_ratio": 1.6151079136690647, "no_speech_prob": 0.000552739598788321}, {"id": 7, "seek": 2700, "start": 39.0, "end": 44.0, "text": " Ich habe die letzten Koalitionsvertr\u00e4ge mitverhandelt und wir k\u00f6nnen es wirklich wahrlich sehen lassen,", "tokens": [3141, 6015, 978, 18226, 10509, 304, 2451, 3281, 40917, 2194, 331, 5543, 2018, 674, 1987, 6310, 785, 9696, 21628, 1739, 11333, 16168, 11], "temperature": 0.0, "avg_logprob": -0.14485943108274227, "compression_ratio": 1.6151079136690647, "no_speech_prob": 0.000552739598788321}, {"id": 8, "seek": 2700, "start": 44.0, "end": 51.0, "text": " wie wir diese Krisen gemeistert haben. Liebe Freunde und Freunde, lasst mich nur kurze Beispiele daf\u00fcr nennen.", "tokens": [3355, 1987, 6705, 28486, 268, 18111, 1964, 83, 3084, 13, 28790, 40016, 674, 40016, 11, 2439, 372, 6031, 4343, 10072, 1381, 879, 7631, 15949, 13747, 297, 16043, 13], "temperature": 0.0, "avg_logprob": -0.14485943108274227, "compression_ratio": 1.6151079136690647, "no_speech_prob": 0.000552739598788321}, {"id": 9, "seek": 5100, "start": 51.0, "end": 60.0, "text": " Wir haben ein bundesweit einmaliges Sozialbudget, das Matthias Wagner hatte schon erw\u00e4hnt, von 35 auf 130 Millionen erh\u00f6ht haben.", "tokens": [4347, 3084, 1343, 13882, 279, 28019, 11078, 20609, 36867, 18281, 847, 11, 1482, 11327, 4609, 38146, 13299, 4981, 21715, 6860, 580, 11, 2957, 6976, 2501, 19966, 26096, 49058, 357, 3084, 13], "temperature": 0.0, "avg_logprob": -0.15870274842240428, "compression_ratio": 1.6406779661016948, "no_speech_prob": 0.00011060654651373625}, {"id": 10, "seek": 5100, "start": 60.0, "end": 66.0, "text": " Das sind nicht nur einfache Zahlen, liebe Freundinnen und Freunde. Wir haben Frauen geholfen, die vor Gewalt fl\u00fcchten.", "tokens": [2846, 3290, 1979, 4343, 38627, 6000, 44096, 11, 31623, 29685, 11399, 674, 40016, 13, 4347, 3084, 24191, 1519, 5449, 6570, 11, 978, 4245, 19063, 3198, 932, 774, 21043, 13], "temperature": 0.0, "avg_logprob": -0.15870274842240428, "compression_ratio": 1.6406779661016948, "no_speech_prob": 0.00011060654651373625}, {"id": 11, "seek": 5100, "start": 66.0, "end": 72.0, "text": " Wir haben Frauenhauspl\u00e4tze geschaffen. Wir haben Jugendliche geholfen, die keine Ausbildungspl\u00e4tze mehr finden,", "tokens": [4347, 3084, 24191, 71, 8463, 564, 30179, 13511, 19182, 13, 4347, 3084, 35303, 10185, 1519, 5449, 6570, 11, 978, 9252, 9039, 16248, 5846, 564, 30179, 5417, 20734, 11], "temperature": 0.0, "avg_logprob": -0.15870274842240428, "compression_ratio": 1.6406779661016948, "no_speech_prob": 0.00011060654651373625}, {"id": 12, "seek": 5100, "start": 72.0, "end": 77.0, "text": " weil die Firmen vor der Insolvenz standen. Wir haben Langzeitarbeitslosen geholfen, die keine Perspektive mehr hatten,", "tokens": [7689, 978, 28164, 2558, 4245, 1163, 9442, 401, 553, 89, 1463, 268, 13, 4347, 3084, 13313, 13712, 289, 21604, 75, 6441, 1519, 5449, 6570, 11, 978, 9252, 14006, 23533, 488, 5417, 20441, 11], "temperature": 0.0, "avg_logprob": -0.15870274842240428, "compression_ratio": 1.6406779661016948, "no_speech_prob": 0.00011060654651373625}, {"id": 13, "seek": 7700, "start": 77.0, "end": 83.0, "text": " den wir Arbeitsmarktprogramme aufgelegt haben. Wir haben nat\u00fcrlich auch denjenigen geholfen, die in Not waren,", "tokens": [1441, 1987, 23262, 38552, 32726, 1398, 35031, 22745, 3084, 13, 4347, 3084, 8762, 2168, 1441, 48176, 1519, 5449, 6570, 11, 978, 294, 1726, 11931, 11], "temperature": 0.0, "avg_logprob": -0.15003080146257267, "compression_ratio": 1.832142857142857, "no_speech_prob": 8.349269046448171e-05}, {"id": 14, "seek": 7700, "start": 83.0, "end": 89.0, "text": " durch Beratungsstrukturen, die wir damit halten. Liebe Freundinnen und Freunde, wir haben in den Koalitionsvertr\u00e4gen versprochen,", "tokens": [7131, 5637, 267, 5846, 372, 19977, 9873, 11, 978, 1987, 9479, 27184, 13, 28790, 29685, 11399, 674, 40016, 11, 1987, 3084, 294, 1441, 10509, 304, 2451, 3281, 11397, 1766, 1774, 23902, 11], "temperature": 0.0, "avg_logprob": -0.15003080146257267, "compression_ratio": 1.832142857142857, "no_speech_prob": 8.349269046448171e-05}, {"id": 15, "seek": 7700, "start": 89.0, "end": 93.0, "text": " dass wir f\u00fcr die soziale Sicherheit und das f\u00fcr soziale Gerechtigkeit sorgen.", "tokens": [2658, 1987, 2959, 978, 31541, 68, 38778, 674, 1482, 2959, 31541, 68, 460, 48561, 16626, 47972, 13], "temperature": 0.0, "avg_logprob": -0.15003080146257267, "compression_ratio": 1.832142857142857, "no_speech_prob": 8.349269046448171e-05}, {"id": 16, "seek": 7700, "start": 93.0, "end": 98.0, "text": " Liebe Freundinnen und Freunde, ihr k\u00f6nnt bei den Wahlk\u00e4mpfen an den St\u00e4nden sagen, wir haben Wort gehalten.", "tokens": [28790, 29685, 11399, 674, 40016, 11, 5553, 22541, 4643, 1441, 27437, 21036, 45316, 364, 1441, 745, 5524, 268, 8360, 11, 1987, 3084, 22748, 1519, 15022, 13], "temperature": 0.0, "avg_logprob": -0.15003080146257267, "compression_ratio": 1.832142857142857, "no_speech_prob": 8.349269046448171e-05}, {"id": 17, "seek": 7700, "start": 98.0, "end": 102.0, "text": " Gr\u00fcne Hessen stehen f\u00fcr soziale Gerechtigkeit, liebe Freundinnen und Freunde.", "tokens": [38908, 716, 24951, 19777, 2959, 31541, 68, 460, 48561, 16626, 11, 31623, 29685, 11399, 674, 40016, 13], "temperature": 0.0, "avg_logprob": -0.15003080146257267, "compression_ratio": 1.832142857142857, "no_speech_prob": 8.349269046448171e-05}, {"id": 18, "seek": 10200, "start": 102.0, "end": 114.0, "text": " Aber machen wir uns nichts vor. Die wirklichen Krise, die noch l\u00e4uft, der Krieg in der Ukraine, die Abrechnung kommen erst noch im M\u00e4rz.", "tokens": [5992, 7069, 1987, 2693, 13004, 4245, 13, 3229, 9696, 268, 6332, 908, 11, 978, 3514, 31807, 11, 1163, 35579, 70, 294, 1163, 14081, 11, 978, 2847, 265, 1377, 1063, 11729, 11301, 3514, 566, 46084, 89, 13], "temperature": 0.0, "avg_logprob": -0.2489588920106279, "compression_ratio": 1.5714285714285714, "no_speech_prob": 0.0004372443363536149}, {"id": 19, "seek": 10200, "start": 114.0, "end": 120.0, "text": " Und die Menschen werden davon geschockt sein und sie werden Probleme haben bei der Energie-Grise.", "tokens": [2719, 978, 8397, 4604, 18574, 13511, 1560, 83, 6195, 674, 2804, 4604, 32891, 3084, 4643, 1163, 35309, 12, 38, 18619, 13], "temperature": 0.0, "avg_logprob": -0.2489588920106279, "compression_ratio": 1.5714285714285714, "no_speech_prob": 0.0004372443363536149}, {"id": 20, "seek": 10200, "start": 120.0, "end": 125.0, "text": " Sie werden von Energie-St\u00e4rf-Sperren bedroht sein. Sie werden von K\u00fcndigungen bedroht sein.", "tokens": [3559, 4604, 2957, 35309, 12, 4520, 2713, 69, 12, 50, 610, 1095, 2901, 340, 357, 6195, 13, 3559, 4604, 2957, 591, 9541, 328, 5084, 2901, 340, 357, 6195, 13], "temperature": 0.0, "avg_logprob": -0.2489588920106279, "compression_ratio": 1.5714285714285714, "no_speech_prob": 0.0004372443363536149}, {"id": 21, "seek": 12500, "start": 125.0, "end": 132.0, "text": " Was wir jetzt brauchen, ist ein weiteres Entlastungspaket f\u00fcr Hessen, in dem wir daf\u00fcr sorgen, dass alles nicht eintritt.", "tokens": [3027, 1987, 4354, 19543, 11, 1418, 1343, 8988, 279, 3951, 15459, 1063, 4952, 514, 302, 2959, 24951, 11, 294, 1371, 1987, 13747, 47972, 11, 2658, 7874, 1979, 308, 686, 18579, 13], "temperature": 0.0, "avg_logprob": -0.1748108350313627, "compression_ratio": 1.6721311475409837, "no_speech_prob": 0.00015842029824852943}, {"id": 22, "seek": 12500, "start": 132.0, "end": 137.0, "text": " Wir m\u00fcssen den Menschen in Not helfen, weil nur das auch unsere Gesellschaft hier in Hessen zusammenh\u00e4lt.", "tokens": [4347, 9013, 1441, 8397, 294, 1726, 29966, 11, 7689, 4343, 1482, 2168, 14339, 30006, 3296, 294, 24951, 14311, 28068, 13], "temperature": 0.0, "avg_logprob": -0.1748108350313627, "compression_ratio": 1.6721311475409837, "no_speech_prob": 0.00015842029824852943}, {"id": 23, "seek": 12500, "start": 137.0, "end": 139.0, "text": " Liebe Freundinnen und Freunde.", "tokens": [28790, 29685, 11399, 674, 40016, 13], "temperature": 0.0, "avg_logprob": -0.1748108350313627, "compression_ratio": 1.6721311475409837, "no_speech_prob": 0.00015842029824852943}, {"id": 24, "seek": 12500, "start": 139.0, "end": 143.0, "text": " Deshalb setzen wir uns ein.", "tokens": [27969, 35877, 1987, 2693, 1343, 13], "temperature": 0.0, "avg_logprob": -0.1748108350313627, "compression_ratio": 1.6721311475409837, "no_speech_prob": 0.00015842029824852943}, {"id": 25, "seek": 12500, "start": 143.0, "end": 151.0, "text": " F\u00fcr das ist keine K\u00fcndigung, dass wir die Beratungsstrukturen st\u00e4rken, dass wir f\u00fcr die Verein- und Einrichtungen, die wir alle brauchen werden,", "tokens": [14990, 1482, 1418, 9252, 591, 9541, 21034, 11, 2658, 1987, 978, 5637, 267, 5846, 372, 19977, 9873, 33527, 2653, 11, 2658, 1987, 2959, 978, 47431, 12, 674, 6391, 12836, 5084, 11, 978, 1987, 5430, 19543, 4604, 11], "temperature": 0.0, "avg_logprob": -0.1748108350313627, "compression_ratio": 1.6721311475409837, "no_speech_prob": 0.00015842029824852943}, {"id": 26, "seek": 12500, "start": 151.0, "end": 154.0, "text": " damit wir den Menschen geholfen werden. Wie beispielsweise den Tafeln.", "tokens": [9479, 1987, 1441, 8397, 1519, 5449, 6570, 4604, 13, 9233, 40152, 1441, 314, 2792, 9878, 13], "temperature": 0.0, "avg_logprob": -0.1748108350313627, "compression_ratio": 1.6721311475409837, "no_speech_prob": 0.00015842029824852943}, {"id": 27, "seek": 15400, "start": 154.0, "end": 159.0, "text": " Es kann einfach nicht sein, dass Menschen, die Hunger erleiden, dass sie zu Tafeln gehen m\u00fcssen.", "tokens": [2313, 4028, 7281, 1979, 6195, 11, 2658, 8397, 11, 978, 46549, 26826, 4380, 11, 2658, 2804, 2164, 314, 2792, 9878, 13230, 9013, 13], "temperature": 0.0, "avg_logprob": -0.15308940410614014, "compression_ratio": 1.7073170731707317, "no_speech_prob": 9.60961333476007e-05}, {"id": 28, "seek": 15400, "start": 159.0, "end": 162.0, "text": " Das finde ich schon schlimm genug, aber dass diese Tafeln ihre Arbeit nicht mehr nachgehen k\u00f6nnen.", "tokens": [2846, 17841, 1893, 4981, 48821, 33194, 11, 4340, 2658, 6705, 314, 2792, 9878, 14280, 18604, 1979, 5417, 5168, 24985, 6310, 13], "temperature": 0.0, "avg_logprob": -0.15308940410614014, "compression_ratio": 1.7073170731707317, "no_speech_prob": 9.60961333476007e-05}, {"id": 29, "seek": 15400, "start": 162.0, "end": 165.0, "text": " Das ist ein Skandal und deswegen haben wir ihnen geholfen.", "tokens": [2846, 1418, 1343, 7324, 18905, 674, 26482, 3084, 1987, 24623, 1519, 5449, 6570, 13], "temperature": 0.0, "avg_logprob": -0.15308940410614014, "compression_ratio": 1.7073170731707317, "no_speech_prob": 9.60961333476007e-05}, {"id": 30, "seek": 15400, "start": 165.0, "end": 169.0, "text": " Es kann nicht sein, dass er ein so einem reichen Land wie Deutschland oder Hessen Menschen hungern m\u00fcssen.", "tokens": [2313, 4028, 1979, 6195, 11, 2658, 1189, 1343, 370, 6827, 319, 18613, 6607, 3355, 14802, 4513, 24951, 8397, 5753, 1248, 9013, 13], "temperature": 0.0, "avg_logprob": -0.15308940410614014, "compression_ratio": 1.7073170731707317, "no_speech_prob": 9.60961333476007e-05}, {"id": 31, "seek": 15400, "start": 169.0, "end": 172.0, "text": " Das muss ein Ende haben, liebe Freundinnen und Freunde.", "tokens": [2846, 6425, 1343, 15152, 3084, 11, 31623, 29685, 11399, 674, 40016, 13], "temperature": 0.0, "avg_logprob": -0.15308940410614014, "compression_ratio": 1.7073170731707317, "no_speech_prob": 9.60961333476007e-05}, {"id": 32, "seek": 17200, "start": 172.0, "end": 182.0, "text": " Wir haben gro\u00dfe Probleme, die vor uns liegen werden.", "tokens": [4347, 3084, 19691, 32891, 11, 978, 4245, 2693, 35100, 4604, 13], "temperature": 0.0, "avg_logprob": -0.26108159516987045, "compression_ratio": 1.5308641975308641, "no_speech_prob": 0.00015597093442920595}, {"id": 33, "seek": 17200, "start": 182.0, "end": 188.0, "text": " Ich werde als Sozialpolitischer Sprecher daf\u00fcr einsetzen, dass wir auf die schw\u00e4chsten Achten werden.", "tokens": [3141, 24866, 3907, 36867, 27461, 19674, 1738, 265, 6759, 13747, 21889, 24797, 11, 2658, 1987, 2501, 978, 17932, 10168, 6266, 316, 21043, 4604, 13], "temperature": 0.0, "avg_logprob": -0.26108159516987045, "compression_ratio": 1.5308641975308641, "no_speech_prob": 0.00015597093442920595}, {"id": 34, "seek": 17200, "start": 188.0, "end": 194.0, "text": " Es kann tats\u00e4chlich werden, wenn wir nicht in den Koalitionsvertr\u00e4gen alles durchsetzen k\u00f6nnen, was gr\u00fcne Programm ist.", "tokens": [2313, 4028, 20796, 4604, 11, 4797, 1987, 1979, 294, 1441, 10509, 304, 2451, 3281, 11397, 1766, 7874, 7131, 3854, 2904, 6310, 11, 390, 677, 21148, 48244, 1418, 13], "temperature": 0.0, "avg_logprob": -0.26108159516987045, "compression_ratio": 1.5308641975308641, "no_speech_prob": 0.00015597093442920595}, {"id": 35, "seek": 17200, "start": 194.0, "end": 201.0, "text": " Aber ich verspreche, dass ich f\u00fcr eine Gesellschaft einsetzen kann, die Anstand vorliebt,", "tokens": [5992, 1893, 1774, 3712, 1876, 11, 2658, 1893, 2959, 3018, 30006, 21889, 24797, 4028, 11, 978, 1107, 1115, 4245, 6302, 4517, 11], "temperature": 0.0, "avg_logprob": -0.26108159516987045, "compression_ratio": 1.5308641975308641, "no_speech_prob": 0.00015597093442920595}, {"id": 36, "seek": 20100, "start": 201.0, "end": 205.0, "text": " die Solidarit\u00e4t vorliebt und die Solidarit\u00e4t mit den Schw\u00e4chten vorliebt.", "tokens": [978, 26664, 289, 14053, 4245, 6302, 4517, 674, 978, 26664, 289, 14053, 2194, 1441, 17576, 10168, 1147, 4245, 6302, 4517, 13], "temperature": 0.0, "avg_logprob": -0.12419957774026054, "compression_ratio": 1.5571955719557196, "no_speech_prob": 4.683782026404515e-05}, {"id": 37, "seek": 20100, "start": 205.0, "end": 209.0, "text": " Gemeinsam in der Landesregierung werden wir gr\u00fcne daf\u00fcr sorgen, dass wir niemanden zur\u00fccklassen.", "tokens": [31266, 1292, 335, 294, 1163, 37695, 4604, 1987, 677, 21148, 13747, 47972, 11, 2658, 1987, 32390, 268, 15089, 44898, 13], "temperature": 0.0, "avg_logprob": -0.12419957774026054, "compression_ratio": 1.5571955719557196, "no_speech_prob": 4.683782026404515e-05}, {"id": 38, "seek": 20100, "start": 209.0, "end": 214.0, "text": " Das ist unsere Fliechenaufgabe und daf\u00fcr stehe ich mit meinem Mandat, liebe Freundinnen und Freunde.", "tokens": [2846, 1418, 14339, 3235, 414, 2470, 9507, 70, 4488, 674, 13747, 2126, 675, 1893, 2194, 24171, 15458, 267, 11, 31623, 29685, 11399, 674, 40016, 13], "temperature": 0.0, "avg_logprob": -0.12419957774026054, "compression_ratio": 1.5571955719557196, "no_speech_prob": 4.683782026404515e-05}, {"id": 39, "seek": 20100, "start": 219.0, "end": 222.0, "text": " Und ein letzter Punkt, der mir sehr am Herzen liegt.", "tokens": [2719, 1343, 14027, 391, 25487, 11, 1163, 3149, 5499, 669, 3204, 2904, 22421, 13], "temperature": 0.0, "avg_logprob": -0.12419957774026054, "compression_ratio": 1.5571955719557196, "no_speech_prob": 4.683782026404515e-05}, {"id": 40, "seek": 20100, "start": 222.0, "end": 227.0, "text": " Wir haben eine unfassbar gro\u00dfe sozialpolitische Herausforderung, das ist die Wohnungsnot.", "tokens": [4347, 3084, 3018, 3971, 640, 5356, 19691, 31541, 27461, 7864, 37888, 1063, 11, 1482, 1418, 978, 22741, 5846, 2247, 13], "temperature": 0.0, "avg_logprob": -0.12419957774026054, "compression_ratio": 1.5571955719557196, "no_speech_prob": 4.683782026404515e-05}, {"id": 41, "seek": 22700, "start": 227.0, "end": 235.0, "text": " Und die war das in vor 2022. Es sind immer wieder neue, mehr soziale Wohnungen aus der Bindung gefallen, als wir geschaffen haben.", "tokens": [2719, 978, 1516, 1482, 294, 4245, 20229, 13, 2313, 3290, 5578, 6216, 16842, 11, 5417, 31541, 68, 22741, 5084, 3437, 1163, 363, 41442, 39935, 11, 3907, 1987, 13511, 19182, 3084, 13], "temperature": 0.0, "avg_logprob": -0.23621729214986165, "compression_ratio": 1.753968253968254, "no_speech_prob": 9.02768224477768e-05}, {"id": 42, "seek": 22700, "start": 235.0, "end": 241.0, "text": " Und wir haben zum ersten Mal Ende 2022 Tarek Al-Wazir, den Trend umzukehrt.", "tokens": [2719, 1987, 3084, 5919, 17324, 5746, 15152, 20229, 314, 543, 74, 967, 12, 54, 921, 347, 11, 1441, 37417, 1105, 11728, 22833, 83, 13], "temperature": 0.0, "avg_logprob": -0.23621729214986165, "compression_ratio": 1.753968253968254, "no_speech_prob": 9.02768224477768e-05}, {"id": 43, "seek": 22700, "start": 241.0, "end": 245.0, "text": " Wir haben zum ersten Mal mehr Sozialbohnungen in Hessen geschaffen, als aus der Bindung gefallen sind.", "tokens": [4347, 3084, 5919, 17324, 5746, 5417, 36867, 65, 2359, 5084, 294, 24951, 13511, 19182, 11, 3907, 3437, 1163, 363, 41442, 39935, 3290, 13], "temperature": 0.0, "avg_logprob": -0.23621729214986165, "compression_ratio": 1.753968253968254, "no_speech_prob": 9.02768224477768e-05}, {"id": 44, "seek": 22700, "start": 245.0, "end": 248.0, "text": " Liebe Freundinnen und Freunde, mit Gr\u00fcnen geht auch Wohnungspolitik.", "tokens": [28790, 29685, 11399, 674, 40016, 11, 2194, 38908, 2866, 7095, 2168, 22741, 5846, 46424, 13], "temperature": 0.0, "avg_logprob": -0.23621729214986165, "compression_ratio": 1.753968253968254, "no_speech_prob": 9.02768224477768e-05}, {"id": 45, "seek": 22700, "start": 248.0, "end": 250.0, "text": " Und das m\u00fcssen wir fortsetzen.", "tokens": [2719, 1482, 9013, 1987, 30589, 24797, 13], "temperature": 0.0, "avg_logprob": -0.23621729214986165, "compression_ratio": 1.753968253968254, "no_speech_prob": 9.02768224477768e-05}, {"id": 46, "seek": 22700, "start": 250.0, "end": 251.0, "text": " Liebe Freundinnen und Freunde.", "tokens": [28790, 29685, 11399, 674, 40016, 13], "temperature": 0.0, "avg_logprob": -0.23621729214986165, "compression_ratio": 1.753968253968254, "no_speech_prob": 9.02768224477768e-05}, {"id": 47, "seek": 25100, "start": 251.0, "end": 260.0, "text": " Wir machen uns nichts vor. Es wird so sein, dass diese Errungenschaften, die wir im Sozialbudget in vielen anderen Paketen geschafft haben,", "tokens": [4347, 7069, 2693, 13004, 4245, 13, 2313, 4578, 370, 6195, 11, 2658, 6705, 3300, 81, 1063, 20996, 268, 11, 978, 1987, 566, 36867, 18281, 847, 294, 19885, 11122, 11543, 19865, 45215, 3084, 11], "temperature": 0.0, "avg_logprob": -0.21031637905406303, "compression_ratio": 1.6867088607594938, "no_speech_prob": 0.00028683902928605676}, {"id": 48, "seek": 25100, "start": 260.0, "end": 265.0, "text": " dass die FDP, die nach dem Motto arbeitet, wenn jeder f\u00fcr sich selbst dog ist, doch allen geholfen,", "tokens": [2658, 978, 31763, 11, 978, 5168, 1371, 8956, 1353, 49907, 11, 4797, 19610, 2959, 3041, 13053, 3000, 1418, 11, 9243, 18440, 1519, 5449, 6570, 11], "temperature": 0.0, "avg_logprob": -0.21031637905406303, "compression_ratio": 1.6867088607594938, "no_speech_prob": 0.00028683902928605676}, {"id": 49, "seek": 25100, "start": 265.0, "end": 269.0, "text": " dass die nur darauf warten, in ihren Antr\u00e4gen, all diese Errungenschaften, diese Erfolger r\u00fcckg\u00e4ngig zu machen.", "tokens": [2658, 978, 4343, 18654, 46907, 11, 294, 22347, 5130, 11397, 1766, 11, 439, 6705, 3300, 81, 1063, 20996, 268, 11, 6705, 3300, 7082, 1321, 367, 6536, 70, 9935, 328, 2164, 7069, 13], "temperature": 0.0, "avg_logprob": -0.21031637905406303, "compression_ratio": 1.6867088607594938, "no_speech_prob": 0.00028683902928605676}, {"id": 50, "seek": 25100, "start": 269.0, "end": 273.0, "text": " Das m\u00fcssen wir verhindern. Wir m\u00fcssen weiter die Anw\u00e4lte der Schw\u00e4chten sein.", "tokens": [2846, 9013, 1987, 1306, 37573, 1248, 13, 4347, 9013, 8988, 978, 1107, 86, 9063, 975, 1163, 17576, 10168, 1147, 6195, 13], "temperature": 0.0, "avg_logprob": -0.21031637905406303, "compression_ratio": 1.6867088607594938, "no_speech_prob": 0.00028683902928605676}, {"id": 51, "seek": 25100, "start": 273.0, "end": 277.0, "text": " Eine Gesellschaft, bei welchem Wert, bemisst sich daran, wie es ihm mit den Schw\u00e4chten umgeht.", "tokens": [17664, 30006, 11, 4643, 2214, 17345, 37205, 11, 7577, 45802, 3041, 24520, 11, 3355, 785, 16021, 2194, 1441, 17576, 10168, 1147, 1105, 46227, 13], "temperature": 0.0, "avg_logprob": -0.21031637905406303, "compression_ratio": 1.6867088607594938, "no_speech_prob": 0.00028683902928605676}, {"id": 52, "seek": 27700, "start": 277.0, "end": 282.0, "text": " Ich setze mich daf\u00fcr ein, dass ihn nach wie vor ihre Hauptaufmerksamkeit darauf legt.", "tokens": [3141, 992, 1381, 6031, 13747, 1343, 11, 2658, 14534, 5168, 3355, 4245, 14280, 30573, 9507, 936, 28665, 9238, 18654, 1676, 83, 13], "temperature": 0.0, "avg_logprob": -0.502396293308424, "compression_ratio": 1.220472440944882, "no_speech_prob": 8.88767244759947e-05}, {"id": 53, "seek": 27700, "start": 282.0, "end": 284.0, "text": " Darauf k\u00f6nnt ihr euch das f\u00fcr die Gespr\u00e4chsprechen.", "tokens": [7803, 9507, 22541, 5553, 10403, 1482, 2959, 978, 38746, 10168, 82, 3712, 2470, 13], "temperature": 0.0, "avg_logprob": -0.502396293308424, "compression_ratio": 1.220472440944882, "no_speech_prob": 8.88767244759947e-05}, {"id": 54, "seek": 28400, "start": 284.0, "end": 308.0, "text": " Danke.", "tokens": [50364, 26508, 13, 51564], "temperature": 0.0, "avg_logprob": -0.7459473133087158, "compression_ratio": 0.42857142857142855, "no_speech_prob": 0.0001223804720211774}], "language": "de", "name": "Marcus Bockelt", "youtube_id": "hmKHLCAvUO0", "summary": "\n\nMarkus Bockler, der sozialpolitische Sprecher der Gr\u00fcnen Landtagsfraktion, betonte die Wichtigkeit sozialer Gerechtigkeit und Solidarit\u00e4t mit den Schw\u00e4chsten. Er erw\u00e4hnte verschiedene Programme, die im Koalitionsvertrag vereinbart wurden, um Menschen in Not zu helfen. Zudem forderte er ein weiteres Entlastungspaket f\u00fcr Hessen sowie mehr Sozialwohnungen und warnte vor einer R\u00fcckg\u00e4ngig-Machen der Errungenschaften durch die FDP.", "buzzword": "\n\n['Soziale Sicherheit', 'Energiekrise', 'Sozialbudget erh\u00f6hen', 'Beratungsstrukturen st\u00e4rken', 'Mehr Sozialwohnungen schaffen']"}